.DS_Store
primosaOAVC2.py
primosaOAVC2022.py
primosaOAVC202202.py
setup.py
build/.DS_Store
build/lib/primos.py
build/lib/setup.py
primosaOAVC202202-0.0.3.dist-info/LICENSE.txt
primosaOAVC202202-0.0.3.dist-info/METADATA
primosaOAVC202202-0.0.3.dist-info/WHEEL
primosaOAVC202202-0.0.3.dist-info/top_level.txt
primosaOAVC202202-0.0.3.dist-info/RECORD
