Metadata-Version: 2.1
Name: primosaOAVC202202
Version: 0.0.3
Summary: Calculate prime numbers
License: UNKNOWN
Platform: UNKNOWN
License-File: LICENSE.txt
